{
    "vialist" : [
        {
            "id": 1,
            "title": "春吉",
            "lat": 33.589745,
            "lng": 130.405127
        },
        {
            "id": 2,
            "title": "渡辺通4丁目",
            "lat": 33.587957,
            "lng": 130.401222
        },
        {
            "id": 3,
            "title": "天神橋口",
            "lat": 33.592308,
            "lng": 130.398390
        },
        {
            "id": 4,
            "title": "舞鶴",
            "lat": 33.591034,
            "lng": 130.394214
        }

    ]
}